{
  "BR_STOCKS": [
    "PETR4.SA","VALE3.SA","ITUB4.SA","BBDC4.SA","BBAS3.SA","ABEV3.SA","WEGE3.SA","SUZB3.SA","JBSS3.SA","GGBR4.SA",
    "CSNA3.SA","KLBN11.SA","PRIO3.SA","ELET3.SA","EMBR3.SA","BRFS3.SA","EGIE3.SA","CPFE3.SA","TAEE11.SA","EQTL3.SA",
    "CPLE6.SA","CMIG4.SA","SANB11.SA","ITSA4.SA","VIVT3.SA","TIMS3.SA","RENT3.SA","LREN3.SA","MGLU3.SA","B3SA3.SA",
    "PETZ3.SA","HYPE3.SA","RADL3.SA","FLRY3.SA","PSSA3.SA","BBSE3.SA","MULT3.SA","BRAP4.SA","MRVE3.SA","CYRE3.SA",
    "EZTC3.SA","DIRR3.SA","COGN3.SA","YDUQ3.SA","SULA11.SA","GOLL4.SA","AZUL4.SA","CCRO3.SA","ENBR3.SA","MRFG3.SA",
    "BEEF3.SA","RAIZ4.SA","RAIL3.SA","CSAN3.SA","UGPA3.SA","ALPA4.SA","NTCO3.SA","CMIN3.SA","ASAI3.SA","ARZZ3.SA"
  ],

  "BR_FIIS": [
    "MXRF11.SA","HGLG11.SA","KNRI11.SA","IRDM11.SA","VISC11.SA","XPML11.SA","XPLG11.SA","BCFF11.SA","GGRC11.SA","HGBS11.SA",
    "HCTR11.SA","RECR11.SA","BTLG11.SA","DEVA11.SA","RZTR11.SA","RBRF11.SA","RBRR11.SA","RBRP11.SA","HGRE11.SA","HGRU11.SA",
    "VRTA11.SA","VILG11.SA","VINO11.SA","RECT11.SA","KNCR11.SA","KNIP11.SA","KNHY11.SA","MCCI11.SA","CVBI11.SA","CPTS11.SA",
    "HGFF11.SA","RBVA11.SA","RBRY11.SA","RZAK11.SA","ALZR11.SA","BARI11.SA","BCRI11.SA","BRCR11.SA","BTAL11.SA","CARE11.SA",
    "EDFO11B.SA","JPPA11.SA","MALL11.SA","NVIF11B.SA","OUJP11.SA","PATL11.SA","PVBI11.SA","RBED11.SA","RCRB11.SA","SADI11.SA"
  ],

  "US_STOCKS": [
    "AAPL","MSFT","NVDA","AMZN","GOOGL","META","AVGO","TSLA","BRK-B","JPM","JNJ","PG","KO","PEP","XOM","CVX","WMT","HD","COST","MRK",
    "ABBV","PFE","TMO","DIS","NFLX","ORCL","CRM","ADBE","CSCO","AMD","INTC","NKE","MCD","AMAT","IBM","TXN","QCOM","LIN","LLY","UNH",
    "BAC","BMY","CAT","GE","GS","RTX","HON","LOW","UPS","PM","DE","INTU","ISRG","PLD","SCHW","SPGI","MS","MU","NOW"
  ],

  "CRYPTO": [
    "BTC-USD","ETH-USD","USDT-USD","BNB-USD","SOL-USD","XRP-USD","USDC-USD","DOGE-USD","TON-USD","ADA-USD",
    "AVAX-USD","TRX-USD","SHIB-USD","DOT-USD","LINK-USD","MATIC-USD","LTC-USD","BCH-USD","ATOM-USD","ETC-USD",
    "XLM-USD","XMR-USD","NEAR-USD","FIL-USD","HBAR-USD","APT-USD","OP-USD","ARB-USD","SUI-USD","AAVE-USD",
    "MKR-USD","RUNE-USD","EGLD-USD","HNT-USD","STX-USD","IMX-USD","SAND-USD","MANA-USD","AXS-USD","FLOW-USD",
    "FTM-USD","INJ-USD","GRT-USD","RNDR-USD","TIA-USD","PYTH-USD","WIF-USD","FET-USD","KAS-USD","JTO-USD"
  ],

  "BR_DIVIDEND": [
    "TAEE11.SA","BBAS3.SA","PSSA3.SA","ITUB4.SA","BBDC4.SA","EGIE3.SA","CPFE3.SA","CMIG4.SA","TRPL4.SA","ITSA4.SA",
    "SANB11.SA","VIVT3.SA","BBSE3.SA","ALUP11.SA","CPLE6.SA","AESB3.SA","ENBR3.SA","EQTL3.SA","SAPR11.SA","CSMG3.SA"
  ],
  "BR_BLUE_CHIPS": [
    "PETR4.SA","VALE3.SA","ITUB4.SA","BBDC4.SA","BBAS3.SA","ABEV3.SA","WEGE3.SA","PRIO3.SA","VIVT3.SA","RENT3.SA"
  ],
  "BR_SMALL_CAPS": [
    "PETZ3.SA","MGLU3.SA","COGN3.SA","YDUQ3.SA","IRBR3.SA","MULT3.SA","MRVE3.SA","CYRE3.SA","EZTC3.SA","ENJU3.SA"
  ],
   "US_DIVIDEND_EXTENDED": [
    "KO","PG","JNJ","PEP","XOM","CVX","MCD","PFE","MRK","WMT", "T","VZ","MO","UPS","HD","ABBV","CL","KMB","MDT","TGT",
    "ABT","AFL","ADM","CLX","DOV","GPC","LIN","NEE","SPGI","O","PPG","ED","FRT"
  ],
  "US_BLUE_CHIPS_EXTENDED": [
    "AAPL","MSFT","NVDA","AMZN","GOOGL","META","BRK-B","JPM","LLY","UNH", "ABT","ABBV","ACN","ADBE","AMD","AMGN","AIG","AXP","BA","BAC","BK",
    "BKNG","BLK","BMY","C","CMCSA","COF","COP","COST","CRM","CVS","DHR", "DIS","DUK","FDX","GD","GE","GILD","GM","GS","HON","INTC","MDLZ",
    "MET","MMM","PM","PYPL","SBUX","SO","SPG","TMUS","UNP","USB","WFC"
  ],
  "US_SMALL_CAPS_EXTENDED": [
    "NET","ZS","OKTA","DDOG","CRWD","MDB","SNOW","ROKU","PATH","PLTR", "AAP","ABM","ABR","ARC","ACAD","ACIA","KFY","KREF","KRYS","KSS","CNT","KTOS","KW","QUA","LEN"
  ]
}
